segy_lite/__init__.py
segy_lite/__main__.py
segy_lite/segy_header.py
segy_lite/seis_plots.py
segy_lite/assets/segyr0_structure.json
segy_lite/assets/segyr1_structure.json
segy_lite-0.0.4.dist-info/LICENSE
segy_lite-0.0.4.dist-info/METADATA
segy_lite-0.0.4.dist-info/WHEEL
segy_lite-0.0.4.dist-info/top_level.txt
segy_lite-0.0.4.dist-info/RECORD
