Metadata-Version: 2.1
Name: segy-lite
Version: 0.0.4
Summary: Lightweight SEGY Reading and Plotting Tool
Home-page: https://github.com/adclose/segy_lite
Author: Aaron Close
Author-email: adclose@gmail.com
License: UNKNOWN
Platform: UNKNOWN
Classifier: Programming Language :: Python :: 3
Classifier: Programming Language :: Python :: 3.6
Classifier: Programming Language :: Python :: 3.7
Classifier: Programming Language :: Python :: 3.8
Classifier: Intended Audience :: Science/Research
Classifier: Topic :: Scientific/Engineering :: GIS
Classifier: License :: OSI Approved :: Apache Software License
Classifier: Operating System :: OS Independent
Requires-Python: >=3.6
Requires-Dist: descartes
Requires-Dist: ebcdic
Requires-Dist: ibm2ieee
Requires-Dist: matplotlib
Requires-Dist: numpy
Requires-Dist: scipy
Requires-Dist: shapely
